{
    "Previous Close": "138.83",
    "Open": "136.97",
    "Bid": "135.24 x 800",
    "Ask": "135.37 x 800",
    "Day's Range": "134.65 - 137.08",
    "52 Week Range": "106.41 - 154.10",
    "Volume": "1,130,783",
    "Avg. Volume": "1,011,627",
    "Market Cap": "20.5B",
    "Beta (3Y Monthly)": "1.51",
    "PE Ratio (TTM)": "30.43",
    "EPS (TTM)": "4.44",
    "Earnings Date": "2019-10-24",
    "Forward Dividend & Yield": "2.76 (2.02%)",
    "Ex-Dividend Date": "2019-08-30",
    "1y Target Est": 162.15,
    "ticker": "SWK",
    "url": "http://finance.yahoo.com/quote/SWK?p=SWK"
}