{
    "Previous Close": "9.45",
    "Open": "9.36",
    "Bid": "9.29 x 43500",
    "Ask": "9.30 x 27000",
    "Day's Range": "9.24 - 9.45",
    "52 Week Range": "7.41 - 10.56",
    "Volume": "45,716,898",
    "Avg. Volume": "36,603,920",
    "Market Cap": "37.09B",
    "Beta (3Y Monthly)": "0.97",
    "PE Ratio (TTM)": "17.21",
    "EPS (TTM)": "0.54",
    "Earnings Date": "2019-10-23",
    "Forward Dividend & Yield": "0.60 (6.35%)",
    "Ex-Dividend Date": "2019-07-22",
    "1y Target Est": 10.73,
    "ticker": "F",
    "url": "http://finance.yahoo.com/quote/F?p=F"
}