{
    "Previous Close": "53.60",
    "Open": "52.30",
    "Bid": "52.92 x 1000",
    "Ask": "52.92 x 900",
    "Day's Range": "52.21 - 53.96",
    "52 Week Range": "46.10 - 66.03",
    "Volume": "1,402,705",
    "Avg. Volume": "2,128,777",
    "Market Cap": "16.06B",
    "Beta (3Y Monthly)": "1.64",
    "PE Ratio (TTM)": "7.46",
    "EPS (TTM)": "7.10",
    "Earnings Date": "2019-10-16 to 2019-10-21",
    "Forward Dividend & Yield": "1.60 (2.99%)",
    "Ex-Dividend Date": "2019-09-26",
    "1y Target Est": 59.46,
    "ticker": "NUE",
    "url": "http://finance.yahoo.com/quote/NUE?p=NUE"
}